{
  "trades": [
    {
      "data": "2026-07-09",
      "s": "AES",
      "setup": "Agulhada",
      "q": "",
      "pc": "14.76",
      "pa": "",
      "pv": "",
      "dv": "",
      "ps": "14.62",
      "tgt": "15.04",
      "clE": "",
      "exitR": "",
      "pe": "",
      "img1": "",
      "img2": ""
    },
    {
      "data": "2026-07-09",
      "s": "ARMK",
      "setup": "Agulhada",
      "q": "",
      "pc": "57.7",
      "pa": "",
      "pv": "",
      "dv": "",
      "ps": "56.59",
      "tgt": "59.92",
      "clE": "",
      "exitR": "",
      "pe": "",
      "img1": "",
      "img2": ""
    },
    {
      "data": "2026-07-09",
      "s": "BAC",
      "setup": "Agulhada",
      "q": "",
      "pc": "59.32",
      "pa": "",
      "pv": "",
      "dv": "",
      "ps": "58.41",
      "tgt": "61.14",
      "clE": "",
      "exitR": "",
      "pe": "",
      "img1": "",
      "img2": ""
    },
    {
      "data": "2026-07-09",
      "s": "INGM",
      "setup": "Agulhada",
      "q": "",
      "pc": "29.21",
      "pa": "",
      "pv": "",
      "dv": "",
      "ps": "27.58",
      "tgt": "32.47",
      "clE": "",
      "exitR": "",
      "pe": "",
      "img1": "",
      "img2": ""
    },
    {
      "data": "2026-07-09",
      "s": "IVZ",
      "setup": "Agulhada",
      "q": "",
      "pc": "28.53",
      "pa": "",
      "pv": "",
      "dv": "",
      "ps": "27.28",
      "tgt": "31.03",
      "clE": "",
      "exitR": "",
      "pe": "",
      "img1": "",
      "img2": ""
    },
    {
      "data": "2026-07-09",
      "s": "NDAQ",
      "setup": "Agulhada",
      "q": "",
      "pc": "87.31",
      "pa": "",
      "pv": "",
      "dv": "",
      "ps": "83.24",
      "tgt": "95.45",
      "clE": "",
      "exitR": "",
      "pe": "",
      "img1": "",
      "img2": ""
    },
    {
      "data": "2026-07-09",
      "s": "PAG",
      "setup": "Agulhada",
      "q": "",
      "pc": "190.49",
      "pa": "",
      "pv": "",
      "dv": "",
      "ps": "184.07",
      "tgt": "203.33",
      "clE": "",
      "exitR": "",
      "pe": "",
      "img1": "",
      "img2": ""
    },
    {
      "data": "2026-07-09",
      "s": "PEP",
      "setup": "Agulhada",
      "q": "",
      "pc": "137.65",
      "pa": "",
      "pv": "",
      "dv": "",
      "ps": "134.69",
      "tgt": "143.57",
      "clE": "",
      "exitR": "",
      "pe": "",
      "img1": "",
      "img2": ""
    },
    {
      "data": "2026-07-09",
      "s": "R",
      "setup": "Agulhada",
      "q": "",
      "pc": "270.11",
      "pa": "",
      "pv": "",
      "dv": "",
      "ps": "267.94",
      "tgt": "274.45",
      "clE": "",
      "exitR": "",
      "pe": "",
      "img1": "",
      "img2": ""
    },
    {
      "data": "2026-07-09",
      "s": "VOYA",
      "setup": "Agulhada",
      "q": "",
      "pc": "97.15",
      "pa": "",
      "pv": "",
      "dv": "",
      "ps": "96.29",
      "tgt": "98.87",
      "clE": "",
      "exitR": "",
      "pe": "",
      "img1": "",
      "img2": ""
    }
  ]
}